compare_package_ex3/__init__.py
compare_package_ex3/equal.py
compare_package_ex3/greater.py
compare_package_ex3/lower.py
compare_package_ex3/notEqual.py
compare_package_ex3-0.0.1.dist-info/METADATA
compare_package_ex3-0.0.1.dist-info/WHEEL
compare_package_ex3-0.0.1.dist-info/top_level.txt
compare_package_ex3-0.0.1.dist-info/RECORD
